text_to_avatar/__init__.py
text_to_avatar/main.py
text_to_avatar/prompts.py
text_to_avatar-2025.12.21234918.dist-info/METADATA
text_to_avatar-2025.12.21234918.dist-info/WHEEL
text_to_avatar-2025.12.21234918.dist-info/top_level.txt
text_to_avatar-2025.12.21234918.dist-info/RECORD
