Metadata-Version: 2.4
Name: text-to-avatar
Version: 2025.12.21234918
Summary: Text-to-avatar generates visual UI attributes from natural language descriptions of avatars.
Author-email: text-to-avatar <hi@eugene.plus>
License: MIT
Project-URL: Homepage, https://github.com/chigwell/text-to-avatar
Requires-Python: >=3.9
Requires-Dist: langchain-llm7>=0.0.0
Requires-Dist: llmatch-messages>=0.0.0
Requires-Dist: langchain-core>=0.3.0
